truefoundry_sdk/__init__.py
truefoundry_sdk/_wrapped_clients.py
truefoundry_sdk/alerts/__init__.py
truefoundry_sdk/alerts/client.py
truefoundry_sdk/alerts/raw_client.py
truefoundry_sdk/application_versions/__init__.py
truefoundry_sdk/application_versions/client.py
truefoundry_sdk/application_versions/raw_client.py
truefoundry_sdk/applications/__init__.py
truefoundry_sdk/applications/client.py
truefoundry_sdk/applications/raw_client.py
truefoundry_sdk/applications/types/__init__.py
truefoundry_sdk/applications/types/applications_cancel_deployment_response.py
truefoundry_sdk/applications/types/applications_list_request_device_type_filter.py
truefoundry_sdk/applications/types/applications_list_request_lifecycle_stage.py
truefoundry_sdk/artifact_versions/__init__.py
truefoundry_sdk/artifact_versions/client.py
truefoundry_sdk/artifact_versions/raw_client.py
truefoundry_sdk/artifact_versions/types/__init__.py
truefoundry_sdk/artifact_versions/types/stage_artifact_request_manifest.py
truefoundry_sdk/artifacts/__init__.py
truefoundry_sdk/artifacts/client.py
truefoundry_sdk/artifacts/raw_client.py
truefoundry_sdk/base_client.py
truefoundry_sdk/client.py
truefoundry_sdk/clusters/__init__.py
truefoundry_sdk/clusters/client.py
truefoundry_sdk/clusters/raw_client.py
truefoundry_sdk/clusters/types/__init__.py
truefoundry_sdk/clusters/types/clusters_delete_response.py
truefoundry_sdk/core/__init__.py
truefoundry_sdk/core/api_error.py
truefoundry_sdk/core/client_wrapper.py
truefoundry_sdk/core/custom_pagination.py
truefoundry_sdk/core/datetime_utils.py
truefoundry_sdk/core/enum.py
truefoundry_sdk/core/file.py
truefoundry_sdk/core/force_multipart.py
truefoundry_sdk/core/http_client.py
truefoundry_sdk/core/http_response.py
truefoundry_sdk/core/http_sse/__init__.py
truefoundry_sdk/core/http_sse/_api.py
truefoundry_sdk/core/http_sse/_decoders.py
truefoundry_sdk/core/http_sse/_exceptions.py
truefoundry_sdk/core/http_sse/_models.py
truefoundry_sdk/core/jsonable_encoder.py
truefoundry_sdk-0.1.19.dist-info/METADATA
truefoundry_sdk-0.1.19.dist-info/WHEEL
truefoundry_sdk-0.1.19.dist-info/RECORD
